neutrino_api_sdk-1.0.0.dist-info/licenses/LICENSE
neutrinoapi/__init__.py
neutrinoapi/api_helper.py
neutrinoapi/configuration.py
neutrinoapi/neutrinoapi_client.py
neutrinoapi/controllers/__init__.py
neutrinoapi/controllers/base_controller.py
neutrinoapi/controllers/data_tools_controller.py
neutrinoapi/controllers/e_commerce_controller.py
neutrinoapi/controllers/geolocation_controller.py
neutrinoapi/controllers/imaging_controller.py
neutrinoapi/controllers/security_and_networking_controller.py
neutrinoapi/controllers/telephony_controller.py
neutrinoapi/controllers/www_controller.py
neutrinoapi/exceptions/__init__.py
neutrinoapi/exceptions/api_error_exception.py
neutrinoapi/exceptions/api_exception.py
neutrinoapi/http/__init__.py
neutrinoapi/http/api_response.py
neutrinoapi/http/http_call_back.py
neutrinoapi/http/http_method_enum.py
neutrinoapi/http/http_request.py
neutrinoapi/http/http_response.py
neutrinoapi/http/auth/__init__.py
neutrinoapi/http/auth/api_key.py
neutrinoapi/http/auth/user_id.py
neutrinoapi/logging/__init__.py
neutrinoapi/logging/sdk_logger.py
neutrinoapi/logging/configuration/__init__.py
neutrinoapi/logging/configuration/api_logging_configuration.py
neutrinoapi/models/__init__.py
neutrinoapi/models/bad_word_filter_response.py
neutrinoapi/models/bin_lookup_response.py
neutrinoapi/models/blacklist.py
neutrinoapi/models/blocklist_sensor.py
neutrinoapi/models/browser_bot_response.py
neutrinoapi/models/convert_response.py
neutrinoapi/models/domain_lookup_response.py
neutrinoapi/models/email_validate_response.py
neutrinoapi/models/email_verify_response.py
neutrinoapi/models/exec_result.py
neutrinoapi/models/geocode_address_response.py
neutrinoapi/models/geocode_reverse_response.py
neutrinoapi/models/hlr_lookup_response.py
neutrinoapi/models/host_reputation_response.py
neutrinoapi/models/html_element.py
neutrinoapi/models/ip_blocklist_response.py
neutrinoapi/models/ip_info_response.py
neutrinoapi/models/ip_probe_response.py
neutrinoapi/models/location.py
neutrinoapi/models/phone_playback_response.py
neutrino_api_sdk-1.0.0.dist-info/METADATA
neutrino_api_sdk-1.0.0.dist-info/WHEEL
neutrino_api_sdk-1.0.0.dist-info/top_level.txt
neutrino_api_sdk-1.0.0.dist-info/RECORD
